<?xml version="1.0" encoding="utf-8"?>
<deployment>
  <id>58e61627d5af41e1bc8aeafbef74a3fa</id>
  <author>N/A</author>
  <deployer>ZipDeploy</deployer>
  <authorEmail>N/A</authorEmail>
  <message>Created via a push deployment</message>
  <progress></progress>
  <status>Success</status>
  <statusText></statusText>
  <lastSuccessEndTime>2025-10-20T15:52:04.036355Z</lastSuccessEndTime>
  <receivedTime>2025-10-20T15:52:03.5988504Z</receivedTime>
  <startTime>2025-10-20T15:52:03.7394766Z</startTime>
  <endTime>2025-10-20T15:52:04.036355Z</endTime>
  <complete>True</complete>
  <is_temp>False</is_temp>
  <is_readonly>True</is_readonly>
  <project_type>Run-From-Zip</project_type>
  <vsproject_id></vsproject_id>
</deployment>